fastapi_access/__init__.py
fastapi_access/access_control.py
fastapi_access/operation.py
fastapi_access/rule.py
fastapi_access/types.py
fastapi_access-0.1.3.1.dist-info/METADATA
fastapi_access-0.1.3.1.dist-info/WHEEL
fastapi_access-0.1.3.1.dist-info/licenses/LICENSE
fastapi_access-0.1.3.1.dist-info/RECORD
